LICENSE
README.md
pyproject.toml
setup.cfg
setup.py
./README.md
pgdbpool.egg-info/PKG-INFO
pgdbpool.egg-info/SOURCES.txt
pgdbpool.egg-info/dependency_links.txt
pgdbpool.egg-info/requires.txt
pgdbpool.egg-info/top_level.txt
pgdbpool.egg-info/zip-safe
src/__init__.py
src/pool.py