Metadata-Version: 2.1
Name: pgdbpool
Version: 1.0rc2
Summary: A tiny database de-multiplexer primarily scoped for Web- / Application Server.
Author: Claus Prüfer
Author-email: Claus Prüfer <pruefer@webcodex.de>
Project-URL: Homepage, https://github.com/clauspruefer/python-dbpool
Project-URL: Issues, https://github.com/clauspruefer/python-dbpool/issues
Project-URL: Documentation, https://pythondocs.webcodex.de/pgdbpool
Project-URL: Changelog, https://github.com/clauspruefer/python-dbpool/CHANGELOG.md
Classifier: Programming Language :: Python :: 3
Classifier: License :: OSI Approved :: GNU Affero General Public License v3 or later (AGPLv3+)
Classifier: Operating System :: OS Independent
Requires-Python: >=3.8
License-File: LICENSE
